bonk_mcp/__init__.py
bonk_mcp/server.py
bonk_mcp/settings.py
bonk_mcp/utils.py
bonk_mcp/core/jupiter.py
bonk_mcp/core/letsbonk.py
bonk_mcp/tools/__init__.py
bonk_mcp/tools/birdeye.py
bonk_mcp/tools/jupiter.py
bonk_mcp/tools/token_buyer.py
bonk_mcp/tools/token_launcher.py
iflow_mcp_letsbonk_ai_bonk_mcp-0.1.10.dist-info/METADATA
iflow_mcp_letsbonk_ai_bonk_mcp-0.1.10.dist-info/WHEEL
iflow_mcp_letsbonk_ai_bonk_mcp-0.1.10.dist-info/entry_points.txt
iflow_mcp_letsbonk_ai_bonk_mcp-0.1.10.dist-info/RECORD
