Metadata-Version: 2.4
Name: iflow-mcp_letsbonk-ai_bonk-mcp
Version: 0.1.10
Summary: A MCP server for Bonk
Author-email: letsbonk-ai <letsbonkai@gmail.com>
Requires-Python: >=3.11
Requires-Dist: aiohttp>=3.11.18
Requires-Dist: base58>=2.1.0
Requires-Dist: mcp>=1.6.0
Requires-Dist: python-dotenv>=1.1.0
Requires-Dist: solana==0.34.0
Requires-Dist: solders==0.21.0
